rmi_qb_sdk/__init__.py
rmi_qb_sdk/error_codes.py
rmi_qb_sdk-0.4.1.dist-info/LICENSE
rmi_qb_sdk-0.4.1.dist-info/METADATA
rmi_qb_sdk-0.4.1.dist-info/WHEEL
rmi_qb_sdk-0.4.1.dist-info/top_level.txt
rmi_qb_sdk-0.4.1.dist-info/RECORD
