Metadata-Version: 2.1
Name: rmi-qb-sdk
Version: 0.4.1
Summary: Reading & Math Inc Python SDK for Quick Base
Home-page: https://github.com/ReadingandMath/Quickbase-Python-SDK
Author: Kevin Connor
Author-email: kevin.connor@servetogrow.org
License: MIT
Platform: UNKNOWN
Classifier: Programming Language :: Python :: 3
